{
    "clan": "Spider",
    "legality": "twenty festivals edition",
    "stronghold": 12262,
    "personalities": [
        12163,
        11224,
        11928,
        11775,
        12327,
        12483,
        12164,
        11227,
        11775,
        12329,
        12482,
        11927
    ],
    "holdings": [
        11549,
        10571,
        7223,
        12281,
        11141,
        3689,
        11881,
        11552,
        1914,
        11714,
        12269
    ],
    "events": [
        66,
        59
    ]
}
