{
    "clan": "Spider",
    "legality": "twenty festivals edition",
    "stronghold": 12262,
    "personalities": [
        11929,
        11604,
        12170,
        11606,
        11926,
        11772,
        7617,
        11775,
        12161,
        11772,
        11223,
        12331
    ],
    "holdings": [
        1497,
        12439,
        12078,
        12077,
        12426,
        11722,
        5027,
        11553,
        11877,
        614,
        11878
    ],
    "events": [
        12421,
        11711
    ]
}
