{
    "clan": "Dragon",
    "legality": "twenty festivals edition",
    "stronghold": 12259,
    "personalities": [
        11175,
        11166,
        12298,
        8545,
        11900,
        12301,
        12454,
        12297,
        11579,
        11173,
        12108,
        11173
    ],
    "holdings": [
        11561,
        12075,
        2470,
        6494,
        12430,
        7266,
        11548,
        10615,
        11548,
        11555,
        11715
    ],
    "events": [
        2346,
        1400
    ]
}
