{
    "clan": "Lion",
    "legality": "twenty festivals edition",
    "stronghold": 12260,
    "personalities": [
        11179,
        12115,
        12120,
        12121,
        11907,
        12126,
        11185,
        11584,
        12123,
        12120,
        12123,
        11582
    ],
    "holdings": [
        9138,
        6021,
        11723,
        12080,
        12071,
        12427,
        11560,
        6535,
        10189,
        10827,
        4091
    ],
    "events": [
        11546,
        66
    ]
}
