{
    "clan": "Crane",
    "legality": "twenty festivals edition",
    "stronghold": 12258,
    "personalities": [
        12102,
        11572,
        12449,
        11161,
        11572,
        11891,
        12100,
        12096,
        11737,
        11738,
        12446,
        12291
    ],
    "holdings": [
        10615,
        4036,
        11882,
        6494,
        11555,
        11547,
        11561,
        12076,
        11712,
        11713,
        12426
    ],
    "events": [
        331,
        9356
    ]
}
